{

	"loglvl": 2,
	
	"tiempo": 180,

	"ventana": {
		"ancho-px": 512,
		"alto-px": 384,
		"ancho": 200
	},
	
	"escenario": {
		"ancho": 600,
		"alto": 150,
		"y-piso": 135,
		"z-index_personajes": 3
	},
	
	"capas": [
		{
			"imagen_fondo": "data/img/background/default/background_0.png",
			"ancho": 200
		},
		{
			"imagen_fondo": "data/img/background/default/background_1.png",
			"ancho": 226.6
		},
		{
			"imagen_fondo": "data/img/background/default/background_2.png",
			"ancho": 600
		}
	],
	
	"personajes": [
		{
		"nombre": "Jugador",
		"sprites": "data/players/subzero/sprites/",
		"poderes": "data/players/subzero/poderes/",
		"color-alternativo": {
			"h-inicial": 180,
			"h-final": 200,
			"desplazamiento": 50
		},
		"ancho": 40,
		"alto": 70
		}
	],
	
	"pelea": {
		"luchador1": "Jugador",
		"luchador2": "Jugador"
	},
	
	"comandos": {
		"luchador1": {
			"pina baja": 2,
			"patada baja": 1,
			"pina alta": 3,
			"patada alta": 0,
			"cubrirse": 4,
			"lanzar arma": 5
		},
		"luchador2": {
			"pina baja": 2,
			"patada baja": 1,
			"pina alta": 3,
			"patada alta": 0,
			"cubrirse": 4,
			"lanzar arma": 5
		}
	}
}